BotniumPlus/__init__.py
BotniumPlus/.locator/common.cnstore
BotniumPlus/.locator/common_img/272791d8-64ce-41ff-8915-b28c409344e2.jpg
BotniumPlus/.locator/common_img/368ef69c-7a71-4e23-8e4a-0cc6ea0d3e17.jpg
BotniumPlus/.locator/common_img/58ddb9e1-3e31-4bae-a5a0-9545a412d054.jpg
BotniumPlus/.locator/common_img/647b731e-7253-4284-881e-7296d3e1cab6.jpg
BotniumPlus/.locator/common_img/6a9f29de-e376-4106-a792-77cec8930529.jpg
BotniumPlus/.locator/common_img/6ba9c406-aab9-4a81-bef5-698c181b7f1e.jpg
BotniumPlus/.locator/common_img/be3a55dd-8594-434d-b90b-d3a5fed9880e.jpg
BotniumPlus/.locator/common_img/c0a149d3-71a7-43fd-9e36-453acac8712d.jpg
BotniumPlus/.locator/common_img/c8974736-dfc7-4268-872c-fd0f01a98bf2.jpg
BotniumPlus/.locator/common_img/fc652ec2-c1c7-4f89-b3fd-7b1cc51b5b3e.jpg
BotniumPlus/common/__init__.py
BotniumPlus/common/models.py
BotniumPlus/common/utils.py
BotniumPlus/lib/CSharpRPA.dll
BotniumPlus/lib/KeyboardCollection.dll
BotniumPlus/lib/lib/AutoKeyBoard.dll
BotniumPlus/lib/lib/WinRing0.dll
BotniumPlus/lib/lib/WinRing0.sys
BotniumPlus/lib/lib/WinRing0x64.dll
BotniumPlus/lib/lib/WinRing0x64.sys
BotniumPlus/lib/lib/xq_usb_hid.dll
BotniumPlus/logger/__init__.py
botnium_plus-1.0.10.dist-info/METADATA
botnium_plus-1.0.10.dist-info/WHEEL
botnium_plus-1.0.10.dist-info/top_level.txt
botnium_plus-1.0.10.dist-info/RECORD
